whatsappy/__init__.py
whatsappy/client.py
whatsappy-1.1.0.dist-info/LICENSE
whatsappy-1.1.0.dist-info/METADATA
whatsappy-1.1.0.dist-info/WHEEL
whatsappy-1.1.0.dist-info/top_level.txt
whatsappy-1.1.0.dist-info/RECORD
