Metadata-Version: 2.1
Name: whatsappy
Version: 1.1.0
Summary: Python for WhatsApp Business Cloud API
Author-email: Matías Glasner Vivanco <mglasner10@gmail.com>
License: Copyright (c) 2018 The Python Packaging Authority
Project-URL: Homepage, https://github.com/mglasner/whatsappy
Project-URL: Bug Tracker, https://github.com/mglasner/whatsappy/issues
Classifier: Programming Language :: Python :: 3
Classifier: License :: OSI Approved :: MIT License
Classifier: Operating System :: OS Independent
Requires-Python: >=3.9
License-File: LICENSE
